fastapi_forge/__init__.py
fastapi_forge/__main__.py
fastapi_forge/constants.py
fastapi_forge/enums.py
fastapi_forge/logger.py
fastapi_forge/schemas.py
fastapi_forge/type_info_registry.py
fastapi_forge/core/__init__.py
fastapi_forge/core/build.py
fastapi_forge/core/cookiecutter_adapter/__init__.py
fastapi_forge/core/cookiecutter_adapter/adapters.py
fastapi_forge/core/cookiecutter_adapter/protocols.py
fastapi_forge/core/project_validators/__init__.py
fastapi_forge/core/project_validators/protocols.py
fastapi_forge/core/project_validators/validators.py
fastapi_forge/core/template_processors/__init__.py
fastapi_forge/core/template_processors/processors.py
fastapi_forge/core/template_processors/protocols.py
fastapi_forge/example-projects/game_zone.yaml
fastapi_forge/frontend/__init__.py
fastapi_forge/frontend/constants.py
fastapi_forge/frontend/main.py
fastapi_forge/frontend/notifications.py
fastapi_forge/frontend/state.py
fastapi_forge/frontend/validation.py
fastapi_forge/frontend/components/__init__.py
fastapi_forge/frontend/components/header.py
fastapi_forge/frontend/components/item_create.py
fastapi_forge/frontend/components/item_row.py
fastapi_forge/frontend/modals/__init__.py
fastapi_forge/frontend/modals/enum_modal.py
fastapi_forge/frontend/modals/field_modal.py
fastapi_forge/frontend/modals/relation_modal.py
fastapi_forge/frontend/panels/__init__.py
fastapi_forge/frontend/panels/enum_editor_panel.py
fastapi_forge/frontend/panels/item_editor_panel.py
fastapi_forge/frontend/panels/left_panel.py
fastapi_forge/frontend/panels/model_editor_panel.py
fastapi_forge/frontend/panels/project_config_panel.py
fastapi_forge/project_io/__init__.py
fastapi_forge/project_io/artifact_builder/__init__.py
fastapi_forge/project_io/artifact_builder/fastapi_builder.py
fastapi_forge/project_io/artifact_builder/protocols.py
fastapi_forge/project_io/artifact_builder/utils.py
fastapi_forge/project_io/database/__init__.py
fastapi_forge/project_io/database/postgres_inspector.py
fastapi_forge-0.13.0.dist-info/licenses/LICENSE
fastapi_forge-0.13.0.dist-info/METADATA
fastapi_forge-0.13.0.dist-info/WHEEL
fastapi_forge-0.13.0.dist-info/entry_points.txt
fastapi_forge-0.13.0.dist-info/top_level.txt
fastapi_forge-0.13.0.dist-info/RECORD
