Metadata-Version: 2.4
Name: fastapi-forge
Version: 0.13.0
Summary: Generate FastAPI projects based on database schema.
Author-email: mslaursen <mslaursendk@gmail.com>
Project-URL: Repository, https://github.com/mslaursen/fastapi-forge.git
Requires-Python: >=3.12
License-File: LICENSE
Requires-Dist: click
Requires-Dist: nicegui
Requires-Dist: cookiecutter
Requires-Dist: pytest
Requires-Dist: ruff
Requires-Dist: psycopg2-binary>=2.9.10
Requires-Dist: inflect>=7.5.0
Requires-Dist: pytest-cov>=6.1.1
Requires-Dist: mypy>=1.15.0
Dynamic: license-file
